kekkai/__init__.py
kekkai/__main__.py
kekkai/cli.py
kekkai/errors.py
kekkai/jj.py
kekkai-0.1.3.dist-info/METADATA
kekkai-0.1.3.dist-info/WHEEL
kekkai-0.1.3.dist-info/entry_points.txt
kekkai-0.1.3.dist-info/RECORD
