Metadata-Version: 2.4
Name: kekkai
Version: 0.1.3
Summary: Minimal CLI wrapper that launches Claude Code in isolated jj workspaces
Author: yum0e
License-Expression: MIT
Keywords: agent,claude,jj,jujutsu,workspace
Classifier: Development Status :: 3 - Alpha
Classifier: Environment :: Console
Classifier: Intended Audience :: Developers
Classifier: License :: OSI Approved :: MIT License
Classifier: Programming Language :: Python :: 3.10
Classifier: Programming Language :: Python :: 3.11
Classifier: Programming Language :: Python :: 3.12
Requires-Python: >=3.10
Requires-Dist: rich>=13.0
Provides-Extra: dev
Requires-Dist: pytest>=7.0; extra == 'dev'
